{
  "realm": "cab-realm",
  "displayName": "CAB Application Realm",
  "enabled": true,
  "sslRequired": "external",
  "registrationAllowed": false,
  "loginWithEmailAllowed": true,
  "duplicateEmailsAllowed": false,
  "resetPasswordAllowed": true,
  "editUsernameAllowed": false,
  "bruteForceProtected": true,
  "accessTokenLifespan": 300,
  "ssoSessionMaxLifespan": 36000,
  "ssoSessionIdleTimeout": 1800,
  "roles": {
    "realm": [
      {
        "name": "REQUESTER",
        "description": "Роль для пользователей, которые могут заказывать такси"
      },
      {
        "name": "EXECUTOR",
        "description": "Роль для водителей такси"
      },
      {
        "name": "CAB_MANAGER",
        "description": "Роль для менеджеров такси-службы"
      },
      {
        "name": "ADMIN",
        "description": "Роль администратора системы"
      }
    ]
  },
  "clients": [
    {
      "clientId": "cab-frontend",
      "name": "CAB Frontend Application",
      "enabled": true,
      "publicClient": true,
      "redirectUris": [
        "http://localhost:5173/*",
        "http://localhost:3000/*",
        "http://localhost:5173",
        "http://localhost:3000"
      ],
      "webOrigins": [
        "http://localhost:5173",
        "http://localhost:3000"
      ],
      "standardFlowEnabled": true,
      "implicitFlowEnabled": false,
      "directAccessGrantsEnabled": true,
      "serviceAccountsEnabled": false,
      "protocol": "openid-connect",
      "attributes": {
        "pkce.code.challenge.method": "S256"
      },
      "protocolMappers": [
        {
          "name": "realm roles",
          "protocol": "openid-connect",
          "protocolMapper": "oidc-usermodel-realm-role-mapper",
          "consentRequired": false,
          "config": {
            "access.token.claim": "true",
            "claim.name": "realm_access.roles",
            "jsonType.label": "String",
            "multivalued": "true"
          }
        },
        {
          "name": "username",
          "protocol": "openid-connect",
          "protocolMapper": "oidc-usermodel-property-mapper",
          "consentRequired": false,
          "config": {
            "user.attribute": "username",
            "access.token.claim": "true",
            "claim.name": "preferred_username",
            "jsonType.label": "String"
          }
        }
      ]
    },
    {
      "clientId": "cab-backend",
      "name": "CAB Backend API",
      "enabled": true,
      "publicClient": false,
      "secret": "backend-secret-123",
      "redirectUris": [],
      "webOrigins": [],
      "standardFlowEnabled": false,
      "implicitFlowEnabled": false,
      "directAccessGrantsEnabled": true,
      "serviceAccountsEnabled": true,
      "protocol": "openid-connect",
      "attributes": {},
      "protocolMappers": [
        {
          "name": "realm roles",
          "protocol": "openid-connect",
          "protocolMapper": "oidc-usermodel-realm-role-mapper",
          "consentRequired": false,
          "config": {
            "access.token.claim": "true",
            "claim.name": "realm_access.roles",
            "jsonType.label": "String",
            "multivalued": "true"
          }
        }
      ]
    }
  ],
  "users": [
    {
      "username": "requester_1",
      "email": "requester1@example.com",
      "firstName": "Requester",
      "lastName": "First",
      "enabled": true,
      "emailVerified": true,
      "credentials": [
        {
          "type": "password",
          "value": "requester_1",
          "temporary": false
        }
      ],
      "realmRoles": [
        "REQUESTER"
      ]
    },
    {
      "username": "requester_2",
      "email": "requester2@example.com",
      "firstName": "Requester",
      "lastName": "Second",
      "enabled": true,
      "emailVerified": true,
      "credentials": [
        {
          "type": "password",
          "value": "requester_2",
          "temporary": false
        }
      ],
      "realmRoles": [
        "REQUESTER"
      ]
    },
    {
      "username": "requester_3",
      "email": "requester3@example.com",
      "firstName": "Requester",
      "lastName": "Third",
      "enabled": true,
      "emailVerified": true,
      "credentials": [
        {
          "type": "password",
          "value": "requester_3",
          "temporary": false
        }
      ],
      "realmRoles": [
        "REQUESTER"
      ]
    },
    {
      "username": "executor_1",
      "email": "executor1@example.com",
      "firstName": "Executor",
      "lastName": "First",
      "enabled": true,
      "emailVerified": true,
      "credentials": [
        {
          "type": "password",
          "value": "executor_1",
          "temporary": false
        }
      ],
      "realmRoles": [
        "EXECUTOR"
      ]
    },
    {
      "username": "executor_2",
      "email": "executor2@example.com",
      "firstName": "Executor",
      "lastName": "Second",
      "enabled": true,
      "emailVerified": true,
      "credentials": [
        {
          "type": "password",
          "value": "executor_2",
          "temporary": false
        }
      ],
      "realmRoles": [
        "EXECUTOR"
      ]
    },
    {
      "username": "executor_3",
      "email": "executor3@example.com",
      "firstName": "Executor",
      "lastName": "Third",
      "enabled": true,
      "emailVerified": true,
      "credentials": [
        {
          "type": "password",
          "value": "executor_3",
          "temporary": false
        }
      ],
      "realmRoles": [
        "EXECUTOR"
      ]
    },
    {
      "username": "cab_manager_1",
      "email": "cabmanager1@example.com",
      "firstName": "CAB Manager",
      "lastName": "First",
      "enabled": true,
      "emailVerified": true,
      "credentials": [
        {
          "type": "password",
          "value": "cab_manager_1",
          "temporary": false
        }
      ],
      "realmRoles": [
        "CAB_MANAGER"
      ]
    },
    {
      "username": "cab_manager_2",
      "email": "cabmanager2@example.com",
      "firstName": "CAB Manager",
      "lastName": "Second",
      "enabled": true,
      "emailVerified": true,
      "credentials": [
        {
          "type": "password",
          "value": "cab_manager_2",
          "temporary": false
        }
      ],
      "realmRoles": [
        "CAB_MANAGER"
      ]
    },
    {
      "username": "cab_manager_3",
      "email": "cabmanager3@example.com",
      "firstName": "CAB Manager",
      "lastName": "Third",
      "enabled": true,
      "emailVerified": true,
      "credentials": [
        {
          "type": "password",
          "value": "cab_manager_3",
          "temporary": false
        }
      ],
      "realmRoles": [
        "CAB_MANAGER"
      ]
    },
    {
      "username": "admin",
      "email": "admin@example.com",
      "firstName": "Admin",
      "lastName": "User",
      "enabled": true,
      "emailVerified": true,
      "credentials": [
        {
          "type": "password",
          "value": "admin",
          "temporary": false
        }
      ],
      "realmRoles": [
        "ADMIN"
      ]
    }
  ],
  "defaultRoles": [
    "offline_access",
    "uma_authorization"
  ]
}